pyconcd.py
pyconcd-0.1.0.dist-info/entry_points.txt
pyconcd-0.1.0.dist-info/LICENSE
pyconcd-0.1.0.dist-info/WHEEL
pyconcd-0.1.0.dist-info/METADATA
pyconcd-0.1.0.dist-info/RECORD
