Metadata-Version: 2.1
Name: pyconcd
Version: 0.1.0
Summary: Countdown until the next PyCon.
Home-page: https://github.com/bryanwweber/pyconcd
License: UNKNOWN
Author: Bryan W. Weber
Author-email: bryan.w.weber@gmail.com
Requires-Python: ~=3.5
Classifier: License :: OSI Approved :: MIT License
Classifier: Development Status :: 3 - Alpha
Classifier: Intended Audience :: End Users/Desktop
Requires-Dist: python-dateutil >=2.8.0
Requires-Dist: pyfiglet >=0.8
